README.rst
setup.cfg
setup.py
./src/gp_functions.cpp
./src/gp_functions.h
./src/main.cpp
pyGlobalPlatform/__init__.py
pyGlobalPlatform/globalplatformlib.py
pyGlobalPlatform.egg-info/PKG-INFO
pyGlobalPlatform.egg-info/SOURCES.txt
pyGlobalPlatform.egg-info/dependency_links.txt
pyGlobalPlatform.egg-info/requires.txt
pyGlobalPlatform.egg-info/top_level.txt
src/gp_functions.cpp
src/gp_functions.h
src/main.cpp